Metadata-Version: 1.1
Name: topsis-by-van
Version: 0.1
Summary: Topsis
Home-page: https://github.com/vanshika-angi/topsis
Author: Vanshika Angi
Author-email: angivanshikaangi@gmail.com
License: MIT
Keywords: SOME,MEANINGFULL,KEYWORDS
Platform: UNKNOWN
Classifier: Development Status :: 3 - Alpha
Classifier: Intended Audience :: Developers
Classifier: Topic :: Software Development :: Build Tools
Classifier: License :: OSI Approved :: MIT License
Classifier: Programming Language :: Python :: 3
Classifier: Programming Language :: Python :: 3.4
Classifier: Programming Language :: Python :: 3.5
Classifier: Programming Language :: Python :: 3.6
